vjemmieapi/__init__.py
vjemmieapi/cache.py
vjemmieapi/crud/__init__.py
vjemmieapi/crud/gamingmoment.py
vjemmieapi/crud/goodmorning.py
vjemmieapi/crud/mediatype.py
vjemmieapi/crud/pfmmeme.py
vjemmieapi/crud/reddit.py
vjemmieapi/crud/skribbl.py
vjemmieapi/crud/tidstyv.py
vjemmieapi/db.py
vjemmieapi/exceptions/__init__.py
vjemmieapi/exceptions/handlers.py
vjemmieapi/exceptions/http.py
vjemmieapi/main.py
vjemmieapi/models/__init__.py
vjemmieapi/models/gamingmoment.py
vjemmieapi/models/goodmorning.py
vjemmieapi/models/mediatype.py
vjemmieapi/models/pfmmeme.py
vjemmieapi/models/reddit.py
vjemmieapi/models/skribbl.py
vjemmieapi/models/tidstyv.py
vjemmieapi/schemas/__init__.py
vjemmieapi/schemas/gamingmoment.py
vjemmieapi/schemas/goodmorning.py
vjemmieapi/schemas/mediatype.py
vjemmieapi/schemas/pfm.py
vjemmieapi/schemas/reddit.py
vjemmieapi/schemas/skribbl.py
vjemmieapi/schemas/tidstyv.py
vjemmieapi-0.3.0.dist-info/WHEEL
vjemmieapi-0.3.0.dist-info/METADATA
vjemmieapi-0.3.0.dist-info/RECORD
