Metadata-Version: 2.1
Name: vjemmieapi
Version: 0.3.0
Summary: 
Author: Peder Hovdan Andresen
Author-email: peder.andresen@gmail.com
Requires-Python: >=3.8,<4.0
Classifier: Programming Language :: Python :: 3
Classifier: Programming Language :: Python :: 3.8
Provides-Extra: server
Requires-Dist: aiocache[memcached] (>=0.11.1,<0.12.0)
Requires-Dist: aiomysql (>=0.0.21,<0.0.22)
Requires-Dist: fastapi (>=0.65.1,<0.66.0)
Requires-Dist: sqlalchemy (>=1.4.18,<2.0.0)
Requires-Dist: uvicorn[standard] (>=0.14.0,<0.15.0); extra == "server"
